Blocks/Block_A/Blatt 02/blatt02/2.3e/andgate.vhdl



library ieee;
use ieee.std_logic_1164.all;

entity andgate is
  -- das andgate hat zwei Eingangsports "input1" und "input2" sowie einen Ausgangsport "and_result"
  
  port (
    input1 : in std_logic;
    input2 : in std_logic;
    and_result : out std_logic
  );
end andgate;

architecture rtl of andgate is
  signal and_gate : std_logic;
begin
  and_gate <= input1 and input2 after 10 ns;
  -- Inertial Delay: Nur Impulse >= 10ns werden übertragen, Verzögerung 10ns
  
  and_result <= transport and_gate after 15 ns; -- verzögerte Signalzuweisung aus d)
  -- => Delay summiert sich auf 25 ns 10 ns durch 'inertial delay' und dann 15 ns 
  --    durch 'transport Delay'
end rtl;

Blocks/Block_A/Blatt 02/blatt02/2.3e/andgate_tb.vhdl
library ieee;
use ieee.std_logic_1164.all;

-- create testbench for and_gate
-- can be left empty, since test bench (this file) has no inputs or outputs
entity andgate_tb is
end andgate_tb;

architecture test of andgate_tb is
  -- component declaration, so that it can be instantiated later
  -- must have same name and port list as the entity
  component andgate
      port (
        input1 : in std_logic;
        input2 : in std_logic;
        and_result : out std_logic
      );
  end component;
-- define the signals that will be used in test
  signal a, b, c : std_logic;
-- begin test code
begin
  -- creates an instance of andgate
  and_g: andgate port map(input1 => a, input2 => b, and_result => c);
  
  process begin
    -- *******************************
    -- TEST: Trägheitsverzögerung
    -- *******************************
    -- Initialisierung:
    a <= '0'; 
    b <= '0';
    wait for 30 ns; -- nun stabiles Signal mit Signalwert '1'

    -- Test 1: 
    report "Test 1: Langer Impuls (20 ns)";
    a <= '1'; 
    b <= '1';
    wait for 15 ns;
    a <= '0';
    wait for 30 ns;
    -- erwartet: Signal c wechselt auf '1' nach 15ns, dann zurück auf '0'
    -- => Impuls >= 10ns, daher NICHT unterdrückt

    -- Test 2:
    report "Test 2: Kurzer Impuls (5 ns) - sollte ignoriert werden";
    a <= '0'; 
    b <= '0';
    wait for 30 ns; -- Signal stabilisieren
    a <= '1'; 
    b <= '1';
    wait for 5 ns;  -- ← Nur 5 ns!
    a <= '0';
    wait for 30 ns;
    -- ERWARTET: Signal c bleibt bei permanent bei '0'
    -- => : Sginalwechsle soll unterdrückt werden

    -- Test 3:
    report "Test 3: Kurzer Impuls (1 ns) - sollte ignoriert werden";
    a <= '0'; 
    b <= '0';
    wait for 30 ns; -- Signal stabilisieren
    a <= '1'; 
    b <= '1';
    wait for 1 ns;  -- ← Nur 1 ns!
    a <= '0';
    wait for 30 ns;
    -- ERWARTET: Signal c bleibt bei permanent bei '0'
    -- => : Sginalwechsle soll unterdrückt werden
    

    assert false report "End of test";
    wait;
  end process;
end test;

Blocks/Block_A/Blatt 02/blatt02/2.3e/testbench.vcd
$date
  Sun Oct 26 00:54:30 2025
$end
$version
  GHDL v0
$end
$timescale
  1 fs
$end
$scope module standard $end
$upscope $end
$scope module std_logic_1164 $end
$upscope $end
$scope module andgate_tb $end
$var reg 1 ! a $end
$var reg 1 " b $end
$var reg 1 # c $end
$scope module and_g $end
$var reg 1 $ input1 $end
$var reg 1 % input2 $end
$var reg 1 & and_result $end
$var reg 1 ' and_gate $end
$upscope $end
$upscope $end
$enddefinitions $end
#0
0!
0"
U#
0$
0%
U&
U'
#10000000
0'
#15000000
U&
#25000000
0#
0&
#30000000
1!
1"
1$
1%
#40000000
1'
#45000000
0!
0$
#55000000
1#
1&
0'
#70000000
0#
0&
#75000000
0"
0%
#85000000
#105000000
1!
1"
1$
1%
#110000000
0!
0$
#120000000
#140000000
0"
0%
#150000000
#170000000
1!
1"
1$
1%
#171000000
0!
0$
