Blocks/Block_B/blatt05-4/5.3/jk_flipflop.vhdl
library ieee;
use ieee.std_logic_1164.all;

entity jk_flipflop is
    port(
        j,k, clk, reset : in std_logic;
        Q : out std_logic
    );
end jk_flipflop;

architecture bh of jk_flipflop is
        signal q_int : std_logic;
    begin
        q <= q_int;
        process begin
            wait until rising_edge(clk);
                if (reset = '1') then
                    q_int <= '0';
                elsif (j = '0' and k = '1') then
                    q_int <= '0';
                elsif (j = '1' and k = '0') then
                    q_int <= '1';
                elsif (j = '1' and k = '1') then
                    q_int <= not q_int;
                end if;
        end process;
end bh;

Blocks/Block_B/blatt05-4/5.3/jk_ff_tb.vhdl
library ieee;
use ieee.std_logic_1164.all;

entity jk_ff_tb is
end entity;

architecture testbench of jk_ff_tb is
  component jk_flipflop is
    port (
      J, K, clk, reset : in std_logic;
      Q                : out std_logic
    );
  end component;

  -- Signale für Testbench
  signal J, K, clk, reset : std_logic := '0';
  signal Q                : std_logic;
begin

  -- Instanziierung des Flip-Flops
  uut : jk_flipflop
  port map
  (
    J     => J,
    K     => K,
    clk   => clk,
    reset => reset,
    Q     => Q
  );

  -- Alles in einem Prozess
  process
  begin

    reset <= '0';
    -- Taktzyklus 1: J=1, K=0 (Set) vor Takt setzen
    J <= '1';
    K <= '0';
    wait for 5 ns; -- Signal leicht vor dem Takt
    clk <= '1';
    wait for 10 ns;
    clk <= '0';
    wait for 5 ns;

    -- Taktzyklus 2: J=0, K=1 (Reset) vor Takt setzen
    J <= '0';
    K <= '1';
    wait for 5 ns;
    clk <= '1';
    wait for 10 ns;
    clk <= '0';
    wait for 5 ns;

    -- Taktzyklus 3: J=1, K=1 (Toggle) vor Takt setzen
    J <= '1';
    K <= '1';
    wait for 5 ns;
    clk <= '1';
    wait for 10 ns;
    clk <= '0';
    wait for 5 ns;

    -- Taktzyklus 4: J=0, K=0 (No change) vor Takt setzen
    J <= '0';
    K <= '0';
    wait for 5 ns;
    clk <= '1';
    wait for 10 ns;
    clk <= '0';
    wait for 5 ns;

    -- Signal aktivieren für Reset
    reset <= '1';
    wait for 5 ns;
    clk <= '1';
    wait for 10 ns;
    clk <= '0';
    wait for 5 ns;

    wait;
  end process;

end architecture;

Blocks/Block_B/blatt05-4/5.3/testbench.vcd
$date
  Sat Nov 22 23:35:22 2025
$end
$version
  GHDL v0
$end
$timescale
  1 fs
$end
$scope module standard $end
$upscope $end
$scope module std_logic_1164 $end
$upscope $end
$scope module jk_ff_tb $end
$var reg 1 ! j $end
$var reg 1 " k $end
$var reg 1 # clk $end
$var reg 1 $ reset $end
$var reg 1 % q $end
$scope module uut $end
$var reg 1 & j $end
$var reg 1 ' k $end
$var reg 1 ( clk $end
$var reg 1 ) reset $end
$var reg 1 * q $end
$var reg 1 + q_int $end
$upscope $end
$upscope $end
$enddefinitions $end
#0
1!
0"
0#
0$
U%
1&
0'
0(
0)
U*
U+
#5000000
1#
1%
1(
1*
1+
#15000000
0#
0(
#20000000
0!
1"
0&
1'
#25000000
1#
0%
1(
0*
0+
#35000000
0#
0(
#40000000
1!
1&
#45000000
1#
1%
1(
1*
1+
#55000000
0#
0(
#60000000
0!
0"
0&
0'
#65000000
1#
1(
#75000000
0#
0(
#80000000
1$
1)
#85000000
1#
0%
1(
0*
0+
