Blocks/Block_B/blatt05-4/5.1/norgate.vhdl
library ieee;
use ieee.std_logic_1164.all;

entity norgate is
    -- das norgate hat zwei Eingangsports "input1" und "input2" sowie einen Ausgangsport "and_result"
    port( 
        input1 : in std_logic; 
        input2 : in std_logic; 
        nor_result : out std_logic
    );
end norgate;

architecture rtl of norgate is

  -- internes Signal, bisher nicht nach aussen verbunden
    signal nor_gate : std_logic;
begin
    nor_gate <= input1 nor input2;
     -- internes Signal wird nach aussen verbunden
    nor_result <= nor_gate;
end rtl;

Blocks/Block_B/blatt05-4/5.2/SR_Latch.vhdl
library ieee;
  use ieee.std_logic_1164.all;

entity SR_Latch is
  port (
    S, R     : in  std_logic;
    Q, not_Q : out std_logic
  );
end entity;

architecture Behavioral of SR_Latch is

  -- verwende or NOR-Gatter als Baustein aus Übugn 02
  component norgate is
    port (
      input1     : in  std_logic;
      input2     : in  std_logic;
      nor_result : out std_logic
    );
  end component;
  -- temorale Signale für die Verbindung der Gatter
  signal tmp1 : std_logic;
  signal tmp2 : std_logic;

begin
  -- Instanziierung der NOR-Gatter
  upper_nor: norgate
    port map (
      input1     => S,
      input2     => tmp2,
      nor_result => tmp1
    );

  lower_or: norgate
    port map (
      input1     => R,
      input2     => tmp1,
      nor_result => tmp2
    );
  -- Ausgabezuweisungen
  Q     <= tmp2;
  not_Q <= tmp1;

end architecture;

Blocks/Block_B/blatt05-4/5.1/SR_Latch_tb.vhdl
library ieee;
use ieee.std_logic_1164.all;

entity SR_Latch_tb is
end entity;

architecture testbench of SR_Latch_tb is

  --missing
  component SR_Latch is
    port (
      S, R     : in std_logic;
      Q, not_Q : out std_logic
    );
  end component;

  signal S     : std_logic;
  signal R     : std_logic;
  signal Q     : std_logic;
  signal not_Q : std_logic;
begin
  -- instanziere die zu testende SR-Latch
  lr_latch_inst : SR_Latch
  port map
  (
    S     => S,
    R     => R,
    Q     => Q,
    not_Q => not_Q
  );

  --missing
  process
  begin
    -- vorgegebene Testsequenz
    S <= '1'; -- set
    R <= '0';
    wait for 10 ns;
    S <= '0'; --reset
    R <= '1';
    wait for 10 ns;
    S <= '0'; -- hold
    R <= '0';
    wait for 10 ns;
    S <= '1'; -- invalid
    R <= '1';
    wait for 10 ns;

    -- 5.1.1b Testsequenz: 

    -- Reset
    S <= '0';
    R <= '1';
    wait for 10 ns;
    S <= '0';
    R <= '0';
    wait for 5 ns;

    -- Andere Reihenfolge: Reset kurz, dann Set kurz
    S <= '0';
    R <= '1';
    wait for 5 ns;
    S <= '1';
    R <= '0';
    wait for 5 ns;
    S <= '0';
    R <= '0';
    wait for 10 ns;

    -- Stress: sehr kurze Pulse und nochmal invalid
    S <= '1';
    R <= '0';
    wait for 1 ns;
    S <= '0';
    R <= '1';
    wait for 5 ns;
    S <= '1';
    R <= '1';
    wait for 5 ns;
    S <= '0';
    R <= '1';
    wait for 10 ns;
    S <= '0';
    R <= '0';
    wait for 10 ns;

    -- Invalid: beide '1' (bei NOR-Latch problematisch)
    S <= '1';
    R <= '1';
    wait for 1 ns;
    -- führt zu: "./sr_latch_tb:info: simulation stopped @107ns by --stop-delta=5000\n

    -- Release schnell in 0/0 => Ausgang kann je nach Gate-Verzögerungen verschieden enden also Q=0 oder Q=1
    -- abhängig davon, welches NOR-Gate zuletzt "gearbeitet" hat
    S <= '0';
    R <= '0';
    wait for 10 ns;

    wait;
  end process;
end architecture;

Blocks/Block_B/blatt05-4/5.1/testbench_rs_latch.vcd
$date
  Sat Nov 22 12:54:32 2025
$end
$version
  GHDL v0
$end
$timescale
  1 fs
$end
$scope module standard $end
$upscope $end
$scope module std_logic_1164 $end
$upscope $end
$scope module sr_latch_tb $end
$var reg 1 ! s $end
$var reg 1 " r $end
$var reg 1 # q $end
$var reg 1 $ not_q $end
$scope module lr_latch_inst $end
$var reg 1 % s $end
$var reg 1 & r $end
$var reg 1 ' q $end
$var reg 1 ( not_q $end
$var reg 1 ) tmp1 $end
$var reg 1 * tmp2 $end
$scope module upper_nor $end
$var reg 1 + input1 $end
$var reg 1 , input2 $end
$var reg 1 - nor_result $end
$var reg 1 . nor_gate $end
$upscope $end
$scope module lower_or $end
$var reg 1 / input1 $end
$var reg 1 0 input2 $end
$var reg 1 1 nor_result $end
$var reg 1 2 nor_gate $end
$upscope $end
$upscope $end
$upscope $end
$enddefinitions $end
#0
1!
0"
1#
0$
1%
0&
1'
0(
0)
1*
1+
1,
0-
0.
0/
00
11
12
#10000000
0!
1"
0#
1$
0%
1&
0'
1(
1)
0*
0+
0,
1-
1.
1/
10
01
02
#20000000
0"
0&
0/
#30000000
1!
1"
0$
1%
1&
0(
0)
1+
0-
0.
1/
00
#40000000
0!
1$
0%
1(
1)
0+
1-
1.
10
#50000000
0"
0&
0/
#55000000
1"
1&
1/
#60000000
1!
0"
1#
0$
1%
0&
1'
0(
0)
1*
1+
1,
0-
0.
0/
00
11
12
#65000000
0!
0%
0+
#75000000
1!
1%
1+
#76000000
0!
1"
0#
1$
0%
1&
0'
1(
1)
0*
0+
0,
1-
1.
1/
10
01
02
#81000000
1!
0$
1%
0(
0)
1+
0-
0.
00
#86000000
0!
1$
0%
1(
1)
0+
1-
1.
10
#96000000
0"
0&
0/
#106000000
1!
1"
0$
1%
1&
0(
0)
1+
0-
0.
1/
00
