Blocks/Block_B/blatt06-4/6.3/jk_flipflop.vhdl
library ieee;
use ieee.std_logic_1164.all;

entity jk_flipflop is
  port (
    j, k, clk, reset : in std_logic;
    Q                : out std_logic
  );
end jk_flipflop;

architecture bh of jk_flipflop is
  signal q_int : std_logic;
begin
  q <= q_int;
  process (clk, reset)
  begin
    if (reset = '1') then
      q_int <= '0'; -- synchroner reset
    elsif rising_edge(clk) then

    elsif (j = '0' and k = '1') then
      q_int <= '0';
    elsif (j = '1' and k = '0') then
      q_int <= '1';
    elsif (j = '1' and k = '1') then
      q_int <= not q_int;
    end if;
  end process;
end bh;

Blocks/Block_B/blatt06-4/6.3/sync_counter.vhdl
library ieee;
use ieee.std_logic_1164.all;

entity sync_counter is
  port (
    reset, clk, C, D : in std_logic;
    q1, q0           : out std_logic
  );
end entity;

architecture bh of sync_counter is
  component jk_flipflop is
    port (
      j, k, clk, reset : in std_logic;
      Q                : out std_logic
    );
  end component;
  -- missing
  signal z0             : std_logic;
  signal z1             : std_logic;
  signal j0, k0, j1, k1 : std_logic;

begin

  j1 <= C and (not D) and z0;
  k1 <= (not z0) and C and D;
  j0 <= C and ((not D) or z1);
  k0 <= C and (D or (not z1));

  -- first flipflop
  JK_FF_0 : jk_flipflop
  port map
  (
    j     => j0,
    k     => k0,
    clk   => clk,
    reset => reset,
    Q     => z0
  );

  -- second flipflop
  JK_FF_1 : jk_flipflop
  port map
  (
    j     => j1,
    k     => k1,
    clk   => clk,
    reset => reset,
    Q     => z1
  );
  q0 <= z0;
  q1 <= z1;

end architecture;

Blocks/Block_B/blatt06-4/6.3/sync_counter_c_tb.vhdl
library ieee;
use ieee.std_logic_1164.all;

entity sync_counter_c_tb is
end sync_counter_c_tb;

architecture tb of sync_counter_c_tb is
  component sync_counter is
    port (
      reset, clk, C, D : in std_logic;
      q1, q0           : out std_logic
    );
  end component;
  -- missing

  signal clk, reset, C, D : std_logic := '0';
  signal q0, q1           : std_logic;

begin
  -- missing
  testing : sync_counter
  port map
  (
    reset => reset,
    clk   => clk,
    C     => C,
    D     => D,
    q1    => q1,
    q0    => q0
  );
  process
  begin
    -- Reset aktiv
    reset <= '1';
    C     <= '0';
    D     <= '0';
    clk   <= '0';
    wait for 20 ns;

    reset <= '0';

    -- Simulationsschritte innerhalb eines Prozesses
    -- Beispiel: 4 Takte vorwärts
    C <= '1';
    D <= '0';
    for i in 1 to 4 loop
      clk <= '0';
      wait for 10 ns;
      clk <= '1';
      wait for 10 ns;
    end loop;

    clk   <= '0';
    reset <= '1';
    C     <= '0'; -- stoppe das zählen
    D     <= '0';
    wait for 10 ns;
    clk   <= '0';
    reset <= '0'; -- reset wieder zurücksetzen

    wait for 10 ns;

    -- wiederum 4 Takte vorwärts nach dem reset
    -- hochzählen durch reset wieder ermöglicht
    C <= '1';
    D <= '0';

    for i in 1 to 4 loop
      clk <= '0';
      wait for 10 ns;
      clk <= '1';
      wait for 10 ns;
    end loop;
    wait;
  end process;

end architecture;

Blocks/Block_B/blatt06-4/6.3/testbench_c.vcd
$date
  Sat Nov 29 18:49:51 2025
$end
$version
  GHDL v0
$end
$timescale
  1 fs
$end
$scope module standard $end
$upscope $end
$scope module std_logic_1164 $end
$upscope $end
$scope module sync_counter_c_tb $end
$var reg 1 ! clk $end
$var reg 1 " reset $end
$var reg 1 # c $end
$var reg 1 $ d $end
$var reg 1 % q0 $end
$var reg 1 & q1 $end
$scope module testing $end
$var reg 1 ' reset $end
$var reg 1 ( clk $end
$var reg 1 ) c $end
$var reg 1 * d $end
$var reg 1 + q1 $end
$var reg 1 , q0 $end
$var reg 1 - z0 $end
$var reg 1 . z1 $end
$var reg 1 / j0 $end
$var reg 1 0 k0 $end
$var reg 1 1 j1 $end
$var reg 1 2 k1 $end
$scope module jk_ff_0 $end
$var reg 1 3 j $end
$var reg 1 4 k $end
$var reg 1 5 clk $end
$var reg 1 6 reset $end
$var reg 1 7 q $end
$var reg 1 8 q_int $end
$upscope $end
$scope module jk_ff_1 $end
$var reg 1 9 j $end
$var reg 1 : k $end
$var reg 1 ; clk $end
$var reg 1 < reset $end
$var reg 1 = q $end
$var reg 1 > q_int $end
$upscope $end
$upscope $end
$upscope $end
$enddefinitions $end
#0
0!
1"
0#
0$
0%
0&
1'
0(
0)
0*
0+
0,
0-
0.
0/
00
01
02
03
04
05
16
07
08
09
0:
0;
1<
0=
0>
#20000000
0"
1#
0'
1)
1/
10
13
14
06
0<
#30000000
1!
1(
15
1;
#40000000
0!
1%
0(
1,
1-
11
05
17
18
19
0;
#50000000
1!
1(
15
1;
#60000000
0!
0%
1&
0(
1+
0,
0-
1.
00
01
04
05
07
08
09
0;
1=
1>
#70000000
1!
1(
15
1;
#80000000
0!
1%
0(
1,
1-
11
05
17
18
19
0;
#90000000
1!
1(
15
1;
#100000000
0!
1"
0#
0%
0&
1'
0(
0)
0+
0,
0-
0.
0/
01
03
05
16
07
08
09
0;
1<
0=
0>
#110000000
0"
0'
06
0<
#120000000
1#
1)
1/
10
13
14
#130000000
1!
1(
15
1;
#140000000
0!
1%
0(
1,
1-
11
05
17
18
19
0;
#150000000
1!
1(
15
1;
#160000000
0!
0%
1&
0(
1+
0,
0-
1.
00
01
04
05
07
08
09
0;
1=
1>
#170000000
1!
1(
15
1;
#180000000
0!
1%
0(
1,
1-
11
05
17
18
19
0;
