Blocks/Block_A/Blatt 02/blatt02/2.3d_transport/andgate.vhdl


-- wir verwenden std_logic_1164 aus der IEEE libary
-- diese Datei definiert die Standards fuer logische Werte im elektronischen Design
-- Details finden sich in der Datei std_logic_1164.vhdl in ghdl/libraries/ieee
-- Die IEEE libary definiert auch operatoren und Schluesselwoerter

library ieee;
use ieee.std_logic_1164.all;


entity andgate is
  -- das andgate hat zwei Eingangsports "input1" und "input2" sowie einen Ausgangsport "and_result"
  
  port (
    input1 : in std_logic;
    input2 : in std_logic;
    and_result : out std_logic
  );
end andgate;


architecture rtl of andgate is
  -- internes Signal, bisher nicht nach aussen verbunden
  signal and_gate : std_logic;
  
begin
  -- internes Signal wird entsprechend der benoetigten Funktionalitaet gesetzt (hier: logisches und der Eingabewerte)

  and_gate <= input1 and input2;
  -- internes Signal wird nach aussen verbunden
  and_result <= transport and_gate after 15 ns; -- verzögerte Signalzuweisung
end rtl;

Blocks/Block_A/Blatt 02/blatt02/2.3d_transport/andgate_tb.vhdl
library ieee;
use ieee.std_logic_1164.all;

-- create testbench for and_gate
-- can be left empty, since test bench (this file) has no inputs or outputs
entity andgate_tb is
end andgate_tb;

architecture test of andgate_tb is
  -- component declaration, so that it can be instantiated later
  -- must have same name and port list as the entity
  component andgate
      port (
        input1 : in std_logic;
        input2 : in std_logic;
        and_result : out std_logic
      );
  end component;
-- define the signals that will be used in test
  signal a, b, c : std_logic;
-- begin test code
begin
  -- creates an instance of andgate
  and_g: andgate port map(input1 => a, input2 => b, and_result => c);

  -- teste logische Korrektheit:
  
  process begin
    -- *******************************
    -- TEST: logischer Test von booleschen Operatoren aus b)
    -- *******************************
    a <= '0';
    b <= '0';
    wait for 10 ns;
    a <= '0';
    b <= '1';
    wait for 10 ns;
    a <= '1';
    b <= '0';
    wait for 10 ns;
    a <= '1';
    b <= '1';
    wait for 10 ns;
    a <= 'X';
    b <= 'W';
    wait for 10 ns;

    -- *******************************
    -- TEST: Überprüfung von 'transport-after'-delay
    -- *******************************

    -- Stabilisiere das Signal:
    a <= '0'; 
    b <= '0';
    wait for 30 ns; 
    -- Ausgangssignal nun auf '0', simuliere Impuls: 

    a <= '1'; 
    b <= '1';
    
    -- Check 1: Nach 14ns darf sich nichts geändert haben (von '0' auf '1'),sonst Änderung zu früh!
    wait for 14 ns;
    assert c /= '1' 
      report "FEHLER: Signal hat sich nach 14 ns bereits geändert (zu früh)!" 
      severity error;
    
    -- Check 2: Nach 16ns muss sich etwas geändert haben (von'0' auf '1' annehmen)
    wait for 2 ns;
    assert c = '1' 
      report "FEHLER: Signal hat sich nach 16 ns nicht geändert (Delay funktioniert nicht)!" 
      severity error;
    
    report "Test: Transport Delay korrekt";

    assert false report "End of test";
    wait;
  end process;
end test;

Blocks/Block_A/Blatt 02/blatt02/2.3d_transport/testbench.vcd
$date
  Sun Oct 26 00:09:57 2025
$end
$version
  GHDL v0
$end
$timescale
  1 fs
$end
$scope module standard $end
$upscope $end
$scope module std_logic_1164 $end
$upscope $end
$scope module andgate_tb $end
$var reg 1 ! a $end
$var reg 1 " b $end
$var reg 1 # c $end
$scope module and_g $end
$var reg 1 $ input1 $end
$var reg 1 % input2 $end
$var reg 1 & and_result $end
$var reg 1 ' and_gate $end
$upscope $end
$upscope $end
$enddefinitions $end
#0
0!
0"
U#
0$
0%
U&
0'
#10000000
1"
1%
#15000000
0#
0&
#20000000
1!
0"
1$
0%
#30000000
1"
1%
1'
#40000000
X!
W"
X$
W%
X'
#45000000
1#
1&
#50000000
0!
0"
0$
0%
0'
#55000000
X#
X&
#65000000
0#
0&
#80000000
1!
1"
1$
1%
1'
#94000000
#95000000
1#
1&
