Blocks/Block_A/Blatt 02/blatt02/2.1c_signals/signals_tb.vhdl
library ieee;
use ieee.std_logic_1164.all;

entity signals_tb is
end signals_tb;

architecture test of signals_tb is
  signal a, b, c : std_logic;
begin
  process begin
    -- dies sind nur Beispiel für Tupel die nicht verwendet werden muessen
    -- insgesamt sollen 8 verschiedene Tupel ausgewaehlt werden
    -- Beispiel für ein Tupel mit 2 unterschiedlichen Signalwerten
    a <= 'X';
    b <= 'W';
    wait for 10 ns; -- Ansonsten werden die Zuordnungen für a, b und c gleichzeitig ausgeführt
    c <= a and b;		
    wait for 10 ns; -- Gibt ein Zeitfenster für die Beobachtung der Ausgabe von a und b im GTK Wave
    c <= a or b;		
    wait for 10 ns; -- Gibt ein Zeitfenster für die Beobachtung der Ausgabe von a oder b im GTK Wave
    -- Das Tupel (0,1) das auf jeden Fall ausgewertet werden soll
    a <= '0';
    b <= '1';
    wait for 10 ns;
    c <= a and b;		--c ist 0
    wait for 10 ns;
    c <= a or b;		--c ist 1
    wait for 10 ns;
    -- Ab hier folgen die eigenen Paare:
    -- Tupel (X, W)
    a <= 'X';
    b <= 'W';
    wait for 10 ns;
    c <= a and b; -- c ist X
    wait for 10 ns;
    c <= a or b;  -- c ist X
    wait for 10 ns;
    -- Tupel (0, 1)
     a <= '0';
    b <= '1';
    wait for 10 ns;
    c <= a and b;		--c ist 0
    wait for 10 ns;
    c <= a or b;		--c ist 1
    wait for 10 ns;
    -- Tupel (H , Z)
     a <= 'H';
    b <= 'Z';
    wait for 10 ns;
    c <= a and b;		--c ist x
    wait for 10 ns;
    c <= a or b;		--c ist 1
    wait for 10 ns;
    -- Tupel (H, X)
    a <= 'H';
    b <= 'X';
    wait for 10 ns;
    c <= a and b;		--c ist x
    wait for 10 ns;
    c <= a or b;		--c ist 1
    wait for 10 ns;
    -- Tupel (L, W)
     a <= 'L';
    b <= 'W';
    wait for 10 ns;
    c <= a and b;		--c ist 0
    wait for 10 ns;
    c <= a or b;		--c ist x
    wait for 10 ns;
    -- Tupel (L , Z)
     a <= 'L';
    b <= 'Z';
    wait for 10 ns;
    c <= a and b;		--c ist 0
    wait for 10 ns;
    c <= a or b;		--c ist x
    wait for 10 ns;
    -- Tupel (0, H)
     a <= '0';
    b <= 'H';
    wait for 10 ns;
    c <= a and b;		--c ist 0
    wait for 10 ns;
    c <= a or b;		--c ist 1
    wait for 10 ns;
    -- Tupel (1 , Z)
     a <= '1';
    b <= 'Z';
    wait for 10 ns;
    c <= a and b;		--c ist x
    wait for 10 ns;
    c <= a or b;		--c ist 1
    wait for 10 ns;
    
    -- Beispiele für Tupel die nicht verwendet werden sollten 
    -- (0,1) und (1,0) sind das gleiche Tupel, es sollte also nur eins davon verwendet werden
    a <= '1';
    b <= '0';
    -- (0,0) hat die gleichen Signalwerte, sollte also nicht verwendet werden
    a <= '0';
    b <= '0';
    -- (1,1) hat die gleichen Signalwerte, sollte also nicht verwendet werden
    a <= '1';
    b <= '1';
    assert false report "End of test"; -- Diese Fehlermeldung zeigt, dass der Test erfolgreich beendet wurde
    wait;
  end process;
end test;

Blocks/Block_A/Blatt 02/blatt02/2.1c_signals/testbench.vcd
$date
  Sat Oct 25 13:21:17 2025
$end
$version
  GHDL v0
$end
$timescale
  1 fs
$end
$scope module standard $end
$upscope $end
$scope module std_logic_1164 $end
$upscope $end
$scope module signals_tb $end
$var reg 1 ! a $end
$var reg 1 " b $end
$var reg 1 # c $end
$upscope $end
$enddefinitions $end
#0
X!
W"
U#
#10000000
X#
#20000000
#30000000
0!
1"
#40000000
0#
#50000000
1#
#60000000
X!
W"
#70000000
X#
#80000000
#90000000
0!
1"
#100000000
0#
#110000000
1#
#120000000
H!
Z"
#130000000
X#
#140000000
1#
#150000000
X"
#160000000
X#
#170000000
1#
#180000000
L!
W"
#190000000
0#
#200000000
X#
#210000000
Z"
#220000000
0#
#230000000
X#
#240000000
0!
H"
#250000000
0#
#260000000
1#
#270000000
1!
Z"
#280000000
X#
#290000000
1#
#300000000
1"
